yta_audio_music/__init__.py
yta_audio_music/beats.py
yta_audio_music/experimental/__init__.py
yta_audio_music/experimental/lyrics.py
yta_audio_music/generation.py
yta_audio_music-0.0.1.dist-info/LICENSE
yta_audio_music-0.0.1.dist-info/METADATA
yta_audio_music-0.0.1.dist-info/WHEEL
yta_audio_music-0.0.1.dist-info/RECORD
