Metadata-Version: 2.3
Name: yta-audio-music
Version: 0.0.1
Summary: Youtube Autonomous Audio Music Module.
Author: danialcala94
Author-email: danielalcalavalera@gmail.com
Requires-Python: ==3.9
Classifier: Programming Language :: Python :: 3
Classifier: Programming Language :: Python :: 3.9
Requires-Dist: librosa (>=0.0.1,<9.0.0)
Requires-Dist: scamp (>=0.0.1,<9.0.0)
Requires-Dist: yta_constants (>=0.0.1,<1.0.0)
Requires-Dist: yta_random (>=0.0.1,<1.0.0)
